arxiv_search_mcp/__init__.py
arxiv_search_mcp/__main__.py
arxiv_search_mcp/mcp_server.py
arxiv_search_mcp-0.2.0.dist-info/licenses/LICENSE
arxiv_search_mcp-0.2.0.dist-info/METADATA
arxiv_search_mcp-0.2.0.dist-info/WHEEL
arxiv_search_mcp-0.2.0.dist-info/top_level.txt
arxiv_search_mcp-0.2.0.dist-info/RECORD
