Metadata-Version: 2.4
Name: arxiv-search-mcp
Version: 0.2.0
Summary: Simple MCP server for searching arXiv
Author-email: Mark McDonald <i@ii.net>
License-Expression: Apache-2.0
Project-URL: Homepage, https://github.com/markmcd/arxiv-search-mcp
Project-URL: Issues, https://github.com/markmcd/arxiv-search-mcp/issues
Requires-Python: >=3.9
License-File: LICENSE
Requires-Dist: arxiv
Requires-Dist: mcp[cli]
Dynamic: license-file
